sigma/backends/cortexxdr/__init__.py
sigma/backends/cortexxdr/cortexxdr.py
sigma/pipelines/cortexxdr/__init__.py
sigma/pipelines/cortexxdr/cortexxdr.py
pysigma_backend_cortexxdr-0.1.4.dist-info/LICENSE
pysigma_backend_cortexxdr-0.1.4.dist-info/METADATA
pysigma_backend_cortexxdr-0.1.4.dist-info/WHEEL
pysigma_backend_cortexxdr-0.1.4.dist-info/RECORD
