Metadata-Version: 2.1
Name: pysigma-backend-cortexxdr
Version: 0.1.4
Summary: pySigma CortexXDR backend
Home-page: https://github.com/7RedViolin/pySigma-backend-cortexxdr
License: MIT
Author: Cori Smith
Author-email: cs2718281@gmail.com
Requires-Python: >=3.8,<4.0
Classifier: License :: OSI Approved :: MIT License
Classifier: Programming Language :: Python :: 3
Classifier: Programming Language :: Python :: 3.8
Classifier: Programming Language :: Python :: 3.9
Classifier: Programming Language :: Python :: 3.10
Classifier: Programming Language :: Python :: 3.11
Requires-Dist: pysigma (>=0.11.3)
Project-URL: Repository, https://github.com/7RedViolin/pySigma-backend-cortexxdr
